airflow_providers_onehouse/__init__.py
airflow_providers_onehouse/_version.py
airflow_providers_onehouse/hooks/__init__.py
airflow_providers_onehouse/hooks/onehouse.py
airflow_providers_onehouse/operators/__init__.py
airflow_providers_onehouse/operators/base_onehouse.py
airflow_providers_onehouse/operators/clusters.py
airflow_providers_onehouse/operators/jobs.py
airflow_providers_onehouse/sensors/__init__.py
airflow_providers_onehouse/sensors/base_onehouse.py
airflow_providers_onehouse/sensors/onehouse.py
airflow_providers_onehouse/utils/__init__.py
airflow_providers_onehouse/utils/enums.py
airflow_providers_onehouse/utils/onehouse.py
apache_airflow_providers_onehouse-0.2.4.dist-info/METADATA
apache_airflow_providers_onehouse-0.2.4.dist-info/WHEEL
apache_airflow_providers_onehouse-0.2.4.dist-info/entry_points.txt
apache_airflow_providers_onehouse-0.2.4.dist-info/top_level.txt
apache_airflow_providers_onehouse-0.2.4.dist-info/RECORD
