Metadata-Version: 2.4
Name: apache-airflow-providers-onehouse
Version: 0.2.4
Summary: Apache Airflow Provider for Onehouse
Author-email: Onehouse Team <support@onehouse.ai>
License: Proprietary
Keywords: airflow,onehouse,provider
Classifier: Development Status :: 5 - Production/Stable
Classifier: Intended Audience :: Developers
Classifier: License :: Other/Proprietary License
Classifier: Framework :: Apache Airflow
Classifier: Framework :: Apache Airflow :: Provider
Classifier: Programming Language :: Python :: 3
Classifier: Programming Language :: Python :: 3.10
Classifier: Programming Language :: Python :: 3.11
Classifier: Programming Language :: Python :: 3.12
Requires-Python: >=3.10
Requires-Dist: apache-airflow>=2.9.2
